convention_appearance_finder/__init__.py
convention_appearance_finder/command_line.py
convention_appearance_finder-0.0.1.dist-info/DESCRIPTION.rst
convention_appearance_finder-0.0.1.dist-info/METADATA
convention_appearance_finder-0.0.1.dist-info/RECORD
convention_appearance_finder-0.0.1.dist-info/WHEEL
convention_appearance_finder-0.0.1.dist-info/entry_points.txt
convention_appearance_finder-0.0.1.dist-info/metadata.json
convention_appearance_finder-0.0.1.dist-info/top_level.txt
