Metadata-Version: 2.0
Name: convention-appearance-finder
Version: 0.0.1
Summary: Tool to find appearances of creators and celebs at conventions
Home-page: https://github.com/rrrxr6/convention_appearance_finder
Author: Ryan Roach
Author-email: rrrxr6@gmail.com
License: MIT
Platform: UNKNOWN
Requires-Python: >=3
